tccr.py
tccr-0.1.2.dist-info/WHEEL
tccr-0.1.2.dist-info/METADATA
tccr-0.1.2.dist-info/RECORD
