Metadata-Version: 2.1
Name: tccr
Version: 0.1.2
Summary: A simple library for changing the color of text in the console, in different ways. Even a child will understand :)))
Author: Nikita Finogenov
Requires-Python: >=3.0,<4.0
Classifier: Programming Language :: Python :: 3
